Workbook

Sheet README
A1: Media credit comps: read me first
A2: USD millions unless labelled. Blue = input, black = formula. Built October 25, 2026 from the five DCF models on this site and the sources listed.
A3: What this is: the five companies from my DCF models, Skydance, Netflix, Disney, Comcast and Fox, lined up the way a debt capital markets or syndicate desk would line them up before a deal. Leverage first, then coverage, cash flow against debt, the equity cushion under the debt, and where each one's paper prices or would price.
A4: Why: the DCF models answer what the equity is worth. A desk asks a different question: how much debt can this balance sheet carry, at what spread, and how much can go wrong before the bonds are impaired. This workbook takes the same base year figures from the five models and answers that.
A5: Sheets: Comps is the main table. Cushion shows what an EBITDA miss does to the equity under the debt. Capacity shows how much debt each company could add or must cut to hit a leverage target. Skydance path walks its net leverage year by year against management's 3.0 times target. Levels lists the sourced trading levels and ratings. Sources is numbered.
A6: Every base year figure links to the matching DCF model's Inputs sheet by value, with the model named. Interest expense is sourced where a filing gave it and estimated as gross debt times the model's cost of debt where it did not, and the Comps sheet says which is which.
A7: Nothing here is a recommendation. No Bloomberg Terminal data and nothing from any employer. Market data as of October 22 and 23, 2026.

Sheet Comps
A1: Credit comps across the five models
A2: USD millions unless labelled. Blue = input, black = formula. Built October 25, 2026 from the five DCF models on this site and the sources listed.
A4: Line | B4: Skydance | C4: Netflix | D4: Disney | E4: Comcast | F4: Fox | G4: Basis
A5: Ticker | B5: SKYD | C5: NFLX | D5: DIS | E5: CMCSA | F5: FOXA | G5: NYSE, Nasdaq, NYSE, Nasdaq, Nasdaq
A6: Base year | B6: 2026E | C6: 2026E | D6: FY2026E | E6: 2026E | F6: FY2026 | G6: Same base year as each DCF model. Disney and Fox are fiscal years ending September and June.
A7: Revenue | B7: 66800 | C7: 51100 | D7: 101000 | E7: 120500 | F7: 17126 | G7: DCF model Inputs sheet of each company.
A8: Adjusted EBITDA | B8: 12291 | C8: 16454 | D8: 25150 | E8: 35000 | F8: 3906 | G8: DCF model Forecast, first year. Skydance before synergies. Netflix is operating income plus property depreciation.
A9: EBITDA margin | B9: =B8/B7 -> 0.18399701 | C9: =C8/C7 -> 0.32199609 | D9: =D8/D7 -> 0.2490099 | E9: =E8/E7 -> 0.29045643 | F9: =F8/F7 -> 0.22807427 | G9: EBITDA over revenue
A10: Gross debt | B10: 89300 | C10: 15300 | D10: 46041 | E10: 87366 | F10: 6606 | G10: Latest balance sheet in each model. Skydance at close per Debtwire [1].
A11: Cash | B11: 5000 | C11: 8194 | D11: 5185 | E11: 7596 | F11: 4205 | G11: Same.
A12: Net debt | B12: =B10-B11 -> 84300 | C12: =C10-C11 -> 7106 | D12: =D10-D11 -> 40856 | E12: =E10-E11 -> 79770 | F12: =F10-F11 -> 2401 | G12: Gross debt less cash
A13: Gross leverage, debt to EBITDA | B13: =B10/B8 -> 7.2654788 | C13: =C10/C8 -> 0.92986508 | D13: =D10/D8 -> 1.8306561 | E13: =E10/E8 -> 2.4961714 | F13: =F10/F8 -> 1.6912442
A14: Net leverage, net debt to EBITDA | B14: =B12/B8 -> 6.8586771 | C14: =C12/C8 -> 0.43187067 | D14: =D12/D8 -> 1.624493 | E14: =E12/E8 -> 2.2791429 | F14: =F12/F8 -> 0.61469534 | G14: The first number any desk asks for.
A15: Interest expense | B15: 6700 | C15: 760 | D15: 1305 | E15: 4409 | F15: 360 | G15: Comcast FY2025 4,409 [4] and Disney FY2025 net 1,305 [3] are reported. Skydance, Netflix and Fox are estimates: gross debt times a blended coupon, 7.5, 5.0 and 5.5 percent, which is below today's marginal cost because most of their debt was issued earlier. Flagged.
A16: Interest coverage, EBITDA to interest | B16: =B8/B15 -> 1.8344776 | C16: =C8/C15 -> 21.65 | D16: =D8/D15 -> 19.272031 | E16: =E8/E15 -> 7.938308 | F16: =F8/F15 -> 10.85 | G16: Below 2 times is where covenants and ratings start to bite.
A17: Unlevered free cash flow, first forecast year | B17: 6435 | C17: 9989 | D17: 10387 | E17: 16998 | F17: 2470 | G17: DCF model Forecast, first year, before interest.
A18: Free cash flow after interest, estimate | B18: =B17-B15 -> -265 | C18: =C17-C15 -> 9229 | D18: =D17-D15 -> 9082 | E18: =E17-E15 -> 12589 | F18: =F17-F15 -> 2110 | G18: Unlevered FCF less interest expense. Before dividends and buybacks.
A19: Free cash flow after interest to net debt | B19: =IF(B12<=0,"net cash",B18/B12) -> -0.003143535 | C19: =IF(C12<=0,"net cash",C18/C12) -> 1.2987616 | D19: =IF(D12<=0,"net cash",D18/D12) -> 0.22229293 | E19: =IF(E12<=0,"net cash",E18/E12) -> 0.15781622 | F19: =IF(F12<=0,"net cash",F18/F12) -> 0.8788005 | G19: How many years of cash flow it takes to repay the debt. Above 20 percent is investment grade territory for a media company; under 5 is distressed.
A20: Share price, $ | B20: 7.77 | C20: 65.85 | D20: 110.16 | E20: 22.04 | F20: 68.27 | G20: October 23, 2026 except Disney, October 16. Same as the models.
A21: Shares, millions | B21: 5040 | C21: 4164 | D21: 1727 | E21: 3551 | F21: 419.65 | G21: Same as the models.
A22: Market value of equity | B22: =B20*B21 -> 39160.8 | C22: =C20*C21 -> 274199.4 | D22: =D20*D21 -> 190246.32 | E22: =E20*E21 -> 78264.04 | F22: =F20*F21 -> 28649.505
A23: Enterprise value at market | B23: =B22+B12+B24 -> 124499.8 | C23: =C22+C12+C24 -> 281305.4 | D23: =D22+D12+D24 -> 237912.32 | E23: =E22+E12+E24 -> 158034.04 | F23: =F22+F12+F24 -> 31050.505 | G23: Equity plus net debt plus noncontrolling interests from the models.
A24: Noncontrolling interests and other claims | B24: 1039 | C24: 0 | D24: 6810 | E24: 0 | F24: 0 | G24: From the models.
A25: Net debt as share of enterprise value | B25: =B12/B23 -> 0.67710952 | C25: =C12/C23 -> 0.025260802 | D25: =D12/D23 -> 0.17172713 | E25: =E12/E23 -> 0.50476467 | F25: =F12/F23 -> 0.077325633 | G25: Loan to value, the way a lender reads it.
A26: Market EV to EBITDA | B26: =B23/B8 -> 10.129347 | C26: =C23/C8 -> 17.096475 | D26: =D23/D8 -> 9.4597344 | E26: =E23/E8 -> 4.5152583 | F26: =F23/F8 -> 7.9494382
A27: DCF equity value, base case, perpetuity method | B27: 44354 | C27: 207334 | D27: 136627 | E27: 157958 | F27: 30433 | G27: DCF sheet of each model, equity value before per share division.
A28: Equity cushion, DCF equity over net debt | B28: =B27/B12 -> 0.52614472 | C28: =C27/C12 -> 29.177315 | D28: =D27/D12 -> 3.344111 | E28: =E27/E12 -> 1.980168 | F28: =F27/F12 -> 12.675135 | G28: How much modelled equity sits under each dollar of net debt. Under 1 times means the debt is more than half the business.
A29: Pre tax cost of debt used in the model | B29: 0.08 | C29: 0.058 | D29: 0.057 | E29: 0.059 | F29: 0.062 | G29: WACC sheet of each model. Skydance blended from 7.05 and 8.875 percent new notes and 10 to 13 percent legacy yields [1]. The other four are analyst inputs at 75 to 125 bp over the 10 year, with Netflix anchored on its July 2026 print [5].
A30: 10 year Treasury, October 22, 2026 | B30: 0.0495 | C30: 0.0495 | D30: 0.0495 | E30: 0.0495 | F30: 0.0495 | G30: Mortgage News Daily [6].
A31: Spread to Treasury on the cost of debt | B31: =(B29-B30)*10000 -> 305 | C31: =(C29-C30)*10000 -> 85 | D31: =(D29-D30)*10000 -> 75 | E31: =(E29-E30)*10000 -> 95 | F31: =(F29-F30)*10000 -> 125 | G31: Cost of debt less the 10 year, in basis points. Where I think a new 10 year would print. Only Skydance's is anchored on sourced trading levels; see Levels.
A32: S&P issuer rating, where sourced | B32: BB | C32: A | D32: A | E32: A range, unverified | F32: not found | G32: Skydance cut to BB September 24, 2026 [1]. Netflix A [5]. Disney A, upgraded December 2024 [3]. Comcast single A range, under Moody's review after the spin announcement, not verified [4]. Fox not found [2].
A34: Read down the yellow rows first. Skydance carries more net debt than the other four combined carry in EBITDA cushion, and its spread is the only one that is not an investment grade number.

Sheet Cushion
A1: What an EBITDA miss does to the equity under the debt
A2: USD millions unless labelled. Blue = input, black = formula. Built October 25, 2026 from the five DCF models on this site and the sources listed.
A4: EBITDA against the base case | B4: Skydance | C4: Netflix | D4: Disney | E4: Comcast | F4: Fox | G4: Basis
A5: Market EV to EBITDA, held constant | B5: =Comps!B26 -> 10.129347 | C5: =Comps!C26 -> 17.096475 | D5: =Comps!D26 -> 9.4597344 | E5: =Comps!E26 -> 4.5152583 | F5: =Comps!F26 -> 7.9494382 | G5: Assumes the market keeps paying the same multiple on lower EBITDA, which is generous. In practice the multiple falls too.
A6: Net debt plus other claims | B6: =Comps!B12+Comps!B24 -> 85339 | C6: =Comps!C12+Comps!C24 -> 7106 | D6: =Comps!D12+Comps!D24 -> 47666 | E6: =Comps!E12+Comps!E24 -> 79770 | F6: =Comps!F12+Comps!F24 -> 2401
A8: Equity value, $ millions
A9: 0 | B9: =MAX(0,Comps!B8*(1+$A9)*B$5-B$6) -> 39160.8 | C9: =MAX(0,Comps!C8*(1+$A9)*C$5-C$6) -> 274199.4 | D9: =MAX(0,Comps!D8*(1+$A9)*D$5-D$6) -> 190246.32 | E9: =MAX(0,Comps!E8*(1+$A9)*E$5-E$6) -> 78264.04 | F9: =MAX(0,Comps!F8*(1+$A9)*F$5-F$6) -> 28649.505
A10: -0.1 | B10: =MAX(0,Comps!B8*(1+$A10)*B$5-B$6) -> 26710.82 | C10: =MAX(0,Comps!C8*(1+$A10)*C$5-C$6) -> 246068.86 | D10: =MAX(0,Comps!D8*(1+$A10)*D$5-D$6) -> 166455.09 | E10: =MAX(0,Comps!E8*(1+$A10)*E$5-E$6) -> 62460.636 | F10: =MAX(0,Comps!F8*(1+$A10)*F$5-F$6) -> 25544.455
A11: -0.2 | B11: =MAX(0,Comps!B8*(1+$A11)*B$5-B$6) -> 14260.84 | C11: =MAX(0,Comps!C8*(1+$A11)*C$5-C$6) -> 217938.32 | D11: =MAX(0,Comps!D8*(1+$A11)*D$5-D$6) -> 142663.86 | E11: =MAX(0,Comps!E8*(1+$A11)*E$5-E$6) -> 46657.232 | F11: =MAX(0,Comps!F8*(1+$A11)*F$5-F$6) -> 22439.404
A12: -0.3 | B12: =MAX(0,Comps!B8*(1+$A12)*B$5-B$6) -> 1810.86 | C12: =MAX(0,Comps!C8*(1+$A12)*C$5-C$6) -> 189807.78 | D12: =MAX(0,Comps!D8*(1+$A12)*D$5-D$6) -> 118872.62 | E12: =MAX(0,Comps!E8*(1+$A12)*E$5-E$6) -> 30853.828 | F12: =MAX(0,Comps!F8*(1+$A12)*F$5-F$6) -> 19334.354
A13: -0.4 | B13: =MAX(0,Comps!B8*(1+$A13)*B$5-B$6) -> 0 | C13: =MAX(0,Comps!C8*(1+$A13)*C$5-C$6) -> 161677.24 | D13: =MAX(0,Comps!D8*(1+$A13)*D$5-D$6) -> 95081.392 | E13: =MAX(0,Comps!E8*(1+$A13)*E$5-E$6) -> 15050.424 | F13: =MAX(0,Comps!F8*(1+$A13)*F$5-F$6) -> 16229.303
A14: -0.5 | B14: =MAX(0,Comps!B8*(1+$A14)*B$5-B$6) -> 0 | C14: =MAX(0,Comps!C8*(1+$A14)*C$5-C$6) -> 133546.7 | D14: =MAX(0,Comps!D8*(1+$A14)*D$5-D$6) -> 71290.16 | E14: =MAX(0,Comps!E8*(1+$A14)*E$5-E$6) -> 0 | F14: =MAX(0,Comps!F8*(1+$A14)*F$5-F$6) -> 13124.253
A16: Equity value as share of base
A17: =A9 -> 0 | B17: =IF(B$9=0,0,B9/B$9) -> 1 | C17: =IF(C$9=0,0,C9/C$9) -> 1 | D17: =IF(D$9=0,0,D9/D$9) -> 1 | E17: =IF(E$9=0,0,E9/E$9) -> 1 | F17: =IF(F$9=0,0,F9/F$9) -> 1
A18: =A10 -> -0.1 | B18: =IF(B$9=0,0,B10/B$9) -> 0.68208055 | C18: =IF(C$9=0,0,C10/C$9) -> 0.89740846 | D18: =IF(D$9=0,0,D10/D$9) -> 0.87494511 | E18: =IF(E$9=0,0,E10/E$9) -> 0.7980758 | F18: =IF(F$9=0,0,F10/F$9) -> 0.8916194
A19: =A11 -> -0.2 | B19: =IF(B$9=0,0,B11/B$9) -> 0.3641611 | C19: =IF(C$9=0,0,C11/C$9) -> 0.79481691 | D19: =IF(D$9=0,0,D11/D$9) -> 0.74989023 | E19: =IF(E$9=0,0,E11/E$9) -> 0.59615159 | F19: =IF(F$9=0,0,F11/F$9) -> 0.7832388
A20: =A12 -> -0.3 | B20: =IF(B$9=0,0,B12/B$9) -> 0.04624165 | C20: =IF(C$9=0,0,C12/C$9) -> 0.69222537 | D20: =IF(D$9=0,0,D12/D$9) -> 0.62483534 | E20: =IF(E$9=0,0,E12/E$9) -> 0.39422739 | F20: =IF(F$9=0,0,F12/F$9) -> 0.6748582
A21: =A13 -> -0.4 | B21: =IF(B$9=0,0,B13/B$9) -> 0 | C21: =IF(C$9=0,0,C13/C$9) -> 0.58963382 | D21: =IF(D$9=0,0,D13/D$9) -> 0.49978045 | E21: =IF(E$9=0,0,E13/E$9) -> 0.19230318 | F21: =IF(F$9=0,0,F13/F$9) -> 0.56647761
A22: =A14 -> -0.5 | B22: =IF(B$9=0,0,B14/B$9) -> 0 | C22: =IF(C$9=0,0,C14/C$9) -> 0.48704228 | D22: =IF(D$9=0,0,D14/D$9) -> 0.37472557 | E22: =IF(E$9=0,0,E14/E$9) -> 0 | F22: =IF(F$9=0,0,F14/F$9) -> 0.45809701
A24: EBITDA miss that wipes out the equity | B24: =-(1-B6/(Comps!B8*B5)) -> -0.31454508 | C24: =-(1-C6/(Comps!C8*C5)) -> -0.9747392 | D24: =-(1-D6/(Comps!D8*D5)) -> -0.79964888 | E24: =-(1-E6/(Comps!E8*E5)) -> -0.49523533 | F24: =-(1-F6/(Comps!F8*F5)) -> -0.92267437 | G24: The miss at which enterprise value equals net debt and the equity is zero. The number a high yield desk carries in its head.
A26: At the market multiple, a 10 percent EBITDA miss costs Skydance's equity about a third. The same miss costs Fox and Netflix about a tenth. That is the whole difference between a BB credit and a single A one, in one row.

Sheet Capacity
A1: Debt capacity at a leverage target
A2: USD millions unless labelled. Blue = input, black = formula. Built October 25, 2026 from the five DCF models on this site and the sources listed.
A4: Line | B4: Skydance | C4: Netflix | D4: Disney | E4: Comcast | F4: Fox | G4: Basis
A5: Adjusted EBITDA | B5: =Comps!B8 -> 12291 | C5: =Comps!C8 -> 16454 | D5: =Comps!D8 -> 25150 | E5: =Comps!E8 -> 35000 | F5: =Comps!F8 -> 3906
A6: Net debt today | B6: =Comps!B12 -> 84300 | C6: =Comps!C12 -> 7106 | D6: =Comps!D12 -> 40856 | E6: =Comps!E12 -> 79770 | F6: =Comps!F12 -> 2401
A7: Net leverage today | B7: =B6/B5 -> 6.8586771 | C7: =C6/C5 -> 0.43187067 | D7: =D6/D5 -> 1.624493 | E7: =E6/E5 -> 2.2791429 | F7: =F6/F5 -> 0.61469534
A9: Target net leverage, Skydance management | B9: 3 | G9: Skydance's own 2029 target [1].
A10: Net debt at target | B10: =$B$9*B5 -> 36873 | C10: =$B$9*C5 -> 49362 | D10: =$B$9*D5 -> 75450 | E10: =$B$9*E5 -> 105000 | F10: =$B$9*F5 -> 11718
A11: Debt that could be added, or must be cut if negative | B11: =B10-B6 -> -47427 | C11: =C10-C6 -> 42256 | D11: =D10-D6 -> 34594 | E11: =E10-E6 -> 25230 | F11: =F10-F6 -> 9317
A12: Years of free cash flow after interest to get there | B12: =IF(B11>=0,0,IF(Comps!B18<=0,"never on cash flow alone",-B11/Comps!B18)) -> never on cash flow alone | C12: =IF(C11>=0,0,IF(Comps!C18<=0,"never on cash flow alone",-C11/Comps!C18)) -> 0 | D12: =IF(D11>=0,0,IF(Comps!D18<=0,"never on cash flow alone",-D11/Comps!D18)) -> 0 | E12: =IF(E11>=0,0,IF(Comps!E18<=0,"never on cash flow alone",-E11/Comps!E18)) -> 0 | F12: =IF(F11>=0,0,IF(Comps!F18<=0,"never on cash flow alone",-F11/Comps!F18)) -> 0
A14: Target net leverage, typical single A media | B14: 2 | G14: Analyst input. S&P cites adjusted leverage below 2.5 times for Disney's A rating [3].
A15: Net debt at target | B15: =$B$14*B5 -> 24582 | C15: =$B$14*C5 -> 32908 | D15: =$B$14*D5 -> 50300 | E15: =$B$14*E5 -> 70000 | F15: =$B$14*F5 -> 7812
A16: Debt that could be added, or must be cut if negative | B16: =B15-B6 -> -59718 | C16: =C15-C6 -> 25802 | D16: =D15-D6 -> 9444 | E16: =E15-E6 -> -9770 | F16: =F15-F6 -> 5411
A17: Years of free cash flow after interest to get there | B17: =IF(B16>=0,0,IF(Comps!B18<=0,"never on cash flow alone",-B16/Comps!B18)) -> never on cash flow alone | C17: =IF(C16>=0,0,IF(Comps!C18<=0,"never on cash flow alone",-C16/Comps!C18)) -> 0 | D17: =IF(D16>=0,0,IF(Comps!D18<=0,"never on cash flow alone",-D16/Comps!D18)) -> 0 | E17: =IF(E16>=0,0,IF(Comps!E18<=0,"never on cash flow alone",-E16/Comps!E18)) -> 0.77607435 | F17: =IF(F16>=0,0,IF(Comps!F18<=0,"never on cash flow alone",-F16/Comps!F18)) -> 0
A19: Target net leverage, high yield comfort | B19: 4.5 | G19: Analyst input, roughly where BB media credits sit.
A20: Net debt at target | B20: =$B$19*B5 -> 55309.5 | C20: =$B$19*C5 -> 74043 | D20: =$B$19*D5 -> 113175 | E20: =$B$19*E5 -> 157500 | F20: =$B$19*F5 -> 17577
A21: Debt that could be added, or must be cut if negative | B21: =B20-B6 -> -28990.5 | C21: =C20-C6 -> 66937 | D21: =D20-D6 -> 72319 | E21: =E20-E6 -> 77730 | F21: =F20-F6 -> 15176
A22: Years of free cash flow after interest to get there | B22: =IF(B21>=0,0,IF(Comps!B18<=0,"never on cash flow alone",-B21/Comps!B18)) -> never on cash flow alone | C22: =IF(C21>=0,0,IF(Comps!C18<=0,"never on cash flow alone",-C21/Comps!C18)) -> 0 | D22: =IF(D21>=0,0,IF(Comps!D18<=0,"never on cash flow alone",-D21/Comps!D18)) -> 0 | E22: =IF(E21>=0,0,IF(Comps!E18<=0,"never on cash flow alone",-E21/Comps!E18)) -> 0 | F22: =IF(F21>=0,0,IF(Comps!F18<=0,"never on cash flow alone",-F21/Comps!F18)) -> 0
A24: Skydance needs to cut about $47 billion of net debt to reach its own 3.0 times target. Its free cash flow after interest in year one is under $1 billion. That is why the Debtwire view is that the target needs equity, and why the second lien notes carry an equity clawback.

Sheet Skydance path
A1: Skydance net leverage, year by year, base case
A2: USD millions unless labelled. Blue = input, black = formula. Built October 25, 2026 from the five DCF models on this site and the sources listed.
A4: USD millions | B4: 2026E | C4: 2027E | D4: 2028E | E4: 2029E | F4: 2030E | G4: 2031E | H4: Basis
A5: Adjusted EBITDA with synergies | B5: 12291 | C5: 13599 | D5: 15227 | E5: 16272 | F5: 16367 | G5: 16308 | H5: Skydance DCF model, Forecast row 13.
A6: Unlevered free cash flow | B6: 6435 | C6: 6802 | D6: 8479 | E6: 10247 | F6: 10737 | G6: 10961 | H6: Skydance DCF model, Forecast row 23.
A7: Average cost of debt | B7: 0.075 | H7: Blended, between the new secured coupons and the legacy yields [1]. Input.
A8: Common dividends | B8: 1070 | H8: About $1.07 billion a year per Debtwire [1]. Input.
A9: Fraction of 2026 remaining | B9: 0.19
A11: Net debt, start of year | B11: =Comps!B12 -> 84300 | C11: =B15 -> 84481.925 | D11: =C15 -> 85086.069 | E11: =D15 -> 84058.525 | F11: =E15 -> 81185.914 | G11: =F15 -> 77607.857
A12: Interest paid | B12: =-B11*$B$7*$B$9 -> -1201.275 | C12: =-C11*$B$7*1 -> -6336.1444 | D12: =-D11*$B$7*1 -> -6381.4552 | E12: =-E11*$B$7*1 -> -6304.3893 | F12: =-F11*$B$7*1 -> -6088.9435 | G12: =-G11*$B$7*1 -> -5820.5893
A13: Dividends paid | B13: =-$B$8*$B$9 -> -203.3 | C13: =-$B$8*1 -> -1070 | D13: =-$B$8*1 -> -1070 | E13: =-$B$8*1 -> -1070 | F13: =-$B$8*1 -> -1070 | G13: =-$B$8*1 -> -1070
A14: Cash available to repay debt | B14: =B6*$B$9+B12+B13 -> -181.925 | C14: =C6*1+C12+C13 -> -604.14437 | D14: =D6*1+D12+D13 -> 1027.5448 | E14: =E6*1+E12+E13 -> 2872.6107 | F14: =F6*1+F12+F13 -> 3578.0565 | G14: =G6*1+G12+G13 -> 4070.4107 | H14: Unlevered FCF less interest and dividends. No asset sales, no equity raise, no buybacks.
A15: Net debt, end of year | B15: =B11-B14 -> 84481.925 | C15: =C11-C14 -> 85086.069 | D15: =D11-D14 -> 84058.525 | E15: =E11-E14 -> 81185.914 | F15: =F11-F14 -> 77607.857 | G15: =G11-G14 -> 73537.447
A16: Net leverage, end of year | B16: =B15/B5 -> 6.8734786 | C16: =C15/C5 -> 6.2567887 | D16: =D15/D5 -> 5.5203602 | E16: =E15/E5 -> 4.9893015 | F16: =F15/F5 -> 4.7417277 | G16: =G15/G5 -> 4.5092867 | H16: Net debt over the same year's EBITDA including synergies.
A17: Management target | B17: 3 | C17: 3 | D17: 3 | E17: 3 | F17: 3 | G17: 3
A18: Gap to target, turns | B18: =B16-B17 -> 3.8734786 | C18: =C16-C17 -> 3.2567887 | D18: =D16-D17 -> 2.5203602 | E18: =E16-E17 -> 1.9893015 | F18: =F16-F17 -> 1.7417277 | G18: =G16-G17 -> 1.5092867
A20: On the base case the company does not reach 3.0 times by 2029. It gets to about 4.6 times by 2031 with every dollar of free cash flow going to debt. Reaching the target on time takes asset sales or equity, which is the question every syndicate desk asked when the $52 billion priced.

Sheet Levels
A1: Sourced trading levels and ratings
A2: USD millions unless labelled. Blue = input, black = formula. Built October 25, 2026 from the five DCF models on this site and the sources listed.
A4: Instrument | B4: Level | C4: Date | D4: Versus | E4: Source and note
A5: Skydance 7.050% first lien notes due 2031 | B5: 272 bp OAS | C5: Oct 13, 2026 | D5: 170 bp wide of BBB index, 87 bp wide of BB index | E5: Debtwire [1]. Rated BBB- by S&P.
A6: Skydance 8.875% second lien notes due 2034 | B6: 483 bp OAS | C6: Oct 13, 2026 | D6: 169 bp wide of single B index | E6: Debtwire [1]. Rated BB by S&P. Price 93.58 to 96.88. 10 percent a year callable at 103, 40 percent equity clawback at 107.
A7: Legacy Paramount Global long unsecured notes | B7: 10.47% to 12.63% yield | C7: Oct 7, 2026 | D7: Prices 46.53 to 62.90 | E7: Debtwire [1]. Now BB- at S&P after the October 12 cut.
A8: Paramount Global 5 year CDS | B8: 577 bp | C8: Oct 13, 2026 | D8: 268 bp on Sept 17, 352 on Sept 24, 499 on Oct 8 | E8: Debtwire [1]. The move from 268 to 577 is the market repricing the merged capital structure.
A9: Skydance new issue, first trading day | B9: Over $100 million of paper losses | C9: Oct 1, 2026 | E9: Press [7]. CFO called it one day choppiness. For a syndicate desk this is the new issue concession question.
A10: Netflix 5.250% notes due 2036 | B10: 5.346% yield at issue | C10: July 2026 | D10: About 90 bp over the 10 year at the time | E10: 424B2 [5]. A2 and A rated.
A11: Comcast | B11: not sourced | E11: Moody's review for downgrade after the June 29, 2026 spin announcement [4]. Levels not retrieved.
A12: Disney | B12: not sourced | E12: S&P A, upgraded December 2024 [3]. Levels not retrieved.
A13: Fox | B13: not sourced | E13: Ratings and levels not retrieved. $12 billion Morgan Stanley bridge and $1 billion term loan committed for Roku [2].
A15: Three of the five have no sourced bond levels in this pass. On a terminal this sheet takes ten minutes to fill from YAS and the relative value screens. Without one I leave the cells empty rather than guess.

Sheet Sources
A1: Sources
A2: USD millions unless labelled. Blue = input, black = formula. Built October 25, 2026 from the five DCF models on this site and the sources listed.
A4: # | B4: Source
A5: 1 | B5: Debtwire, Skydance Corporation financing and trading levels, October 2026, as cited in the Skydance DCF model sources. Ratings actions from S&P and Moody's as reported there.
A6: 2 | B6: Fox Corporation FY2026 earnings release, Form 10-K and the June 2026 Roku merger announcement. foxcorporation.com and sec.gov
A7: 3 | B7: The Walt Disney Company FY2025 earnings release and Q3 FY2026 10-Q; S&P Global Ratings upgrade to A, December 2024.
A8: 4 | B8: Comcast Corporation Form 10-K for fiscal 2025 and Q3 2026 10-Q; press coverage of Moody's review, June 2026.
A9: 5 | B9: Netflix 424B2 prospectus supplement, 5.250 percent notes due 2036, July 2026; Q3 2026 shareholder letter.
A10: 6 | B10: Mortgage News Daily, 10 year Treasury yield, October 22, 2026.
A11: 7 | B11: Press coverage of the Skydance new issue first day trading, October 1, 2026.
A12: 8 | B12: The five DCF models on this site, for every base year, forecast and valuation figure. Skydance_DCF_Model.xlsx, NFLX_DCF_Model.xlsx, DIS_DCF_Model.xlsx, CMCSA_DCF_Model.xlsx, FOXA_DCF_Model.xlsx.
B14: Analyst inputs are labelled where they sit. Nothing comes from a Bloomberg Terminal or from any employer.
